aws_db_migration/__init__.py
aws_db_migration/action_enum.py
aws_db_migration/aws_credentials.py
aws_db_migration/database_credentials.py
aws_db_migration/invoke_lambda.py
aws_db_migration/invoke_mysql.py
aws_db_migration/invoke_s3.py
aws_db_migration/mysql_cloud_dump.sh
aws_db_migration/mysql_cloud_restore.sh
aws_db_migration/mysql_local_dump.sh
aws_db_migration/mysql_local_restore.sh
aws_db_migration/run_lambda.py
aws_db_migration/run_local.py
aws_db_migration-3.1.1.dist-info/LICENSE.txt
aws_db_migration-3.1.1.dist-info/METADATA
aws_db_migration-3.1.1.dist-info/WHEEL
aws_db_migration-3.1.1.dist-info/top_level.txt
aws_db_migration-3.1.1.dist-info/RECORD
