Metadata-Version: 2.1
Name: aws-db-migration
Version: 3.1.1
Summary: Management project which can run locally and on AWS Lambda function. Project aims to make database migrations from/to cloud easy.
Home-page: https://github.com/laimonassutkus/AwsDbMigration
Author: Laimonas Sutkus
Author-email: laimonas@myhealthyapps.com
License: UNKNOWN
Keywords: AWS SDK RDS Database Backup Restore Migration Infrastructure Cloud Lambda
Platform: UNKNOWN
Classifier: Programming Language :: Python :: 3
Classifier: Programming Language :: Python :: 3.5
Classifier: Programming Language :: Python :: 3.6
Classifier: Operating System :: POSIX :: Linux
Requires-Dist: boto3
Requires-Dist: botocore
Requires-Dist: python-dotenv (==0.10.3)
